[
    {
        "title": "Dashboard",
        "path": "/",
        "icon": "bi-house-fill mx-1"
      
    },
    {
        "title": "Home",
        "path": "24",
        "icon": "bi-house-fill mx-1"
       
    },
    {
        "title": "Service Management",
        "path": "/Admin",
        "icon": "bi-camera-video mx-1",
        "childrens": [
            {
                "title": "ServiceConfiguration",
                "path": "/Admin",
                "childrens": [
                    {
                        "title": "ServiceCreation",
                        "path": "/servicecreation"
                    },
                    {
                        "title": "ServiceEdit",
                        "path": "/serviceedit"
                    }
                ]
            },
            {
                "title": "ServicePlan Configuration",
                "path": "/serviceplan"
            }
        ]
    },
    
    {
        "title": "User Management",
        "path": "/",
        "icon": "bi-file-earmark-image mx-1",
        "childrens": []
    },
    {
        "title": "Channel Management",
        "path": "/usercreation",
        "icon": "bi-quote mx-1",
        "childrens": []
    },
    {
        "title": "Promotion Management",
        "path": "/AddPost",
        "icon": "bi-newspaper mx-1",
        "childrens": [
            {
                "title": "Post",
                "path": "/AddPost"
            },
            {
                "title": "User Creation",
                "path": "/usercreation"
            }
        ]
    }
]
